Metadata-Version: 2.1
Name: odoo9-addon-l10n-it-base-location-geonames-import
Version: 9.0.0.1.0.99.dev7
Summary: Import base_location entries (provinces) from Geonames
Home-page: http://www.agilebg.com
Author: Agile Business Group,Odoo Community Association (OCA)
Author-email: support@odoo-community.org
License: AGPL-3
Platform: UNKNOWN
Classifier: Programming Language :: Python
Classifier: Framework :: Odoo
Classifier: License :: OSI Approved :: GNU Affero General Public License v3
Requires-Python: ~=2.7
Requires-Dist: odoo9-addon-base-location-geonames-import
Requires-Dist: odoo (<9.1a,>=9.0a)
